QianghuaXuexiDaolunZhongwenDierBanFix1/README.md
QianghuaXuexiDaolunZhongwenDierBanFix1/__init__.py
QianghuaXuexiDaolunZhongwenDierBanFix1/__main__.py
QianghuaXuexiDaolunZhongwenDierBanFix1/file.epub
QianghuaXuexiDaolunZhongwenDierBanFix1/index.html
QianghuaXuexiDaolunZhongwenDierBanFix1/css/__init__.py
QianghuaXuexiDaolunZhongwenDierBanFix1/css/annotations.css
QianghuaXuexiDaolunZhongwenDierBanFix1/css/main.css
QianghuaXuexiDaolunZhongwenDierBanFix1/css/normalize.css
QianghuaXuexiDaolunZhongwenDierBanFix1/css/popup.css
QianghuaXuexiDaolunZhongwenDierBanFix1/font/__init__.py
QianghuaXuexiDaolunZhongwenDierBanFix1/font/fontello.eot
QianghuaXuexiDaolunZhongwenDierBanFix1/font/fontello.svg
QianghuaXuexiDaolunZhongwenDierBanFix1/font/fontello.ttf
QianghuaXuexiDaolunZhongwenDierBanFix1/font/fontello.woff
QianghuaXuexiDaolunZhongwenDierBanFix1/img/__init__.py
QianghuaXuexiDaolunZhongwenDierBanFix1/img/annotator-glyph-sprite.png
QianghuaXuexiDaolunZhongwenDierBanFix1/img/annotator-icon-sprite.png
QianghuaXuexiDaolunZhongwenDierBanFix1/img/apple-touch-icon.png
QianghuaXuexiDaolunZhongwenDierBanFix1/img/cancelfullscreen.png
QianghuaXuexiDaolunZhongwenDierBanFix1/img/close.png
QianghuaXuexiDaolunZhongwenDierBanFix1/img/fullscreen.png
QianghuaXuexiDaolunZhongwenDierBanFix1/img/loader.gif
QianghuaXuexiDaolunZhongwenDierBanFix1/img/menu-icon.png
QianghuaXuexiDaolunZhongwenDierBanFix1/img/save.png
QianghuaXuexiDaolunZhongwenDierBanFix1/img/saved.png
QianghuaXuexiDaolunZhongwenDierBanFix1/img/settings-s.png
QianghuaXuexiDaolunZhongwenDierBanFix1/img/settings.png
QianghuaXuexiDaolunZhongwenDierBanFix1/img/star.png
QianghuaXuexiDaolunZhongwenDierBanFix1/js/__init__.py
QianghuaXuexiDaolunZhongwenDierBanFix1/js/epub.js
QianghuaXuexiDaolunZhongwenDierBanFix1/js/epub.min.js
QianghuaXuexiDaolunZhongwenDierBanFix1/js/epub.min.map
QianghuaXuexiDaolunZhongwenDierBanFix1/js/hooks.min.js
QianghuaXuexiDaolunZhongwenDierBanFix1/js/hooks.min.map
qianghua_xuexi_daolun_zhongwen_dier_ban_fix1-2025.3.24.0.dist-info/METADATA
qianghua_xuexi_daolun_zhongwen_dier_ban_fix1-2025.3.24.0.dist-info/WHEEL
qianghua_xuexi_daolun_zhongwen_dier_ban_fix1-2025.3.24.0.dist-info/entry_points.txt
qianghua_xuexi_daolun_zhongwen_dier_ban_fix1-2025.3.24.0.dist-info/top_level.txt
qianghua_xuexi_daolun_zhongwen_dier_ban_fix1-2025.3.24.0.dist-info/RECORD
